onoffice/__init__.py
onoffice/actions.py
onoffice/api.py
onoffice/cryptography.py
onoffice/parameters.py
onoffice/resources.py
onoffice-0.2.0.dist-info/METADATA
onoffice-0.2.0.dist-info/WHEEL
onoffice-0.2.0.dist-info/RECORD
